definehtml/__init__.py
definehtml/__main__.py
definehtml/define2-1.xsl
definehtml/define2-1.xsl.LICENSE
definehtml/definehtml.py
defineutils-0.1.1.dist-info/licenses/LICENSE
validate/__init__.py
validate/__main__.py
validate/validate.py
validate/schema/cdisc-arm-1.0/arm-extension.xsd
validate/schema/cdisc-arm-1.0/arm-ns.xsd
validate/schema/cdisc-arm-1.0/arm1-0-0.xsd
validate/schema/cdisc-define-2.1/define-enumerations.html
validate/schema/cdisc-define-2.1/define-enumerations.xsd
validate/schema/cdisc-define-2.1/define-extension.xsd
validate/schema/cdisc-define-2.1/define-ns.xsd
validate/schema/cdisc-define-2.1/define2-1-0.xsd
validate/schema/cdisc-odm-1.3.2/ODM1-3-2-foundation.xsd
validate/schema/cdisc-odm-1.3.2/ODM1-3-2.xsd
validate/schema/core/xlink.xsd
validate/schema/core/xml.xsd
validate/schema/core/xmldsig-core-schema.xsd
defineutils-0.1.1.dist-info/METADATA
defineutils-0.1.1.dist-info/WHEEL
defineutils-0.1.1.dist-info/top_level.txt
defineutils-0.1.1.dist-info/RECORD
