Metadata-Version: 2.4
Name: defineutils
Version: 0.1.1
Summary: CDISC Define-XML v2.1 utilities
Author-email: Sam Hume <swhume@gmail.com>
License: MIT License
Project-URL: Homepage, https://github.com/swhume/defineutils
Keywords: define.xml,Define-XML,CDISC
Classifier: License :: OSI Approved :: MIT License
Classifier: Programming Language :: Python
Classifier: Programming Language :: Python :: 3
Requires-Python: >=3.10
License-File: LICENSE
Requires-Dist: elementpath>=5.0.4
Requires-Dist: lxml>=6.0.1
Requires-Dist: xmlschema>=4.1.0
Requires-Dist: tomli; python_version < "3.11"
Dynamic: license-file
